MANIFEST.in
README.md
setup.cfg
setup.py
test_code2006/__init__.py
test_code2006/funct1.py
test_code2006/panda.html
test_code2006/plot.png
test_code2006/plt1.png
test_code2006/vis.jpg
test_code2006.egg-info/PKG-INFO
test_code2006.egg-info/SOURCES.txt
test_code2006.egg-info/dependency_links.txt
test_code2006.egg-info/requires.txt
test_code2006.egg-info/top_level.txt