Metadata-Version: 1.1
Name: test-code2006
Version: 0.1
Summary:  pandas_ui helps you wrangle & explore your data and create custom visualizations without digging through StackOverflow. All inside your Jupyter Notebook or JupyterLab ( alternative to Bamboolib ).
Home-page: https://github.com/arunnbaba/
Author: Arunn Thangavel
Author-email: arunnbabainfo@gmail.com
License: MIT License
Download-URL: https://github.com/arunnbaba/test_code2006/archive/v13.0.zip
Keywords: Pands_ui,bamboolib,ui for pandas
Platform: UNKNOWN
Classifier: Development Status :: 3 - Alpha
Classifier: Intended Audience :: Developers
Classifier: Topic :: Software Development :: Build Tools
Classifier: License :: OSI Approved :: MIT License
Classifier: Programming Language :: Python :: 3.7
